MANIFEST.in
README.md
setup.py
ioexplorer_dataloader/__init__.py
ioexplorer_dataloader.egg-info/PKG-INFO
ioexplorer_dataloader.egg-info/SOURCES.txt
ioexplorer_dataloader.egg-info/dependency_links.txt
ioexplorer_dataloader.egg-info/entry_points.txt
ioexplorer_dataloader.egg-info/requires.txt
ioexplorer_dataloader.egg-info/top_level.txt
ioexplorer_dataloader/cli/__init__.py
ioexplorer_dataloader/cli/common/__init__.py
ioexplorer_dataloader/cli/common/arguments.py
ioexplorer_dataloader/cli/common/constants.py
ioexplorer_dataloader/cli/common/decorators.py
ioexplorer_dataloader/cli/common/logging.py
ioexplorer_dataloader/cli/common/prompts.py
ioexplorer_dataloader/cli/database/__init__.py
ioexplorer_dataloader/cli/database/helpers.py
ioexplorer_dataloader/cli/dataset/__init__.py
ioexplorer_dataloader/cli/dataset/helpers.py
ioexplorer_dataloader/ioexplorer-database-migrations/.git
ioexplorer_dataloader/ioexplorer-database-migrations/000-create-dataset.js
ioexplorer_dataloader/ioexplorer-database-migrations/001-create-subject.js
ioexplorer_dataloader/ioexplorer-database-migrations/002-create-sample.js
ioexplorer_dataloader/ioexplorer-database-migrations/003-create-cna.js
ioexplorer_dataloader/ioexplorer-database-migrations/003-create-expression.js
ioexplorer_dataloader/ioexplorer-database-migrations/003-create-fusions.js
ioexplorer_dataloader/ioexplorer-database-migrations/003-create-mutation.js
ioexplorer_dataloader/ioexplorer-database-migrations/003-create-svs.js
ioexplorer_dataloader/ioexplorer-database-migrations/003-create-tcrsequences.js
ioexplorer_dataloader/ioexplorer-database-migrations/003-create-timeline.js
ioexplorer_dataloader/ioexplorer-database-migrations/004-create-user.js
ioexplorer_dataloader/loaders/BaseLoader.py
ioexplorer_dataloader/loaders/CNALoader.py
ioexplorer_dataloader/loaders/ClinicalSampleLoader.py
ioexplorer_dataloader/loaders/ClinicalSubjectLoader.py
ioexplorer_dataloader/loaders/ExpressionLoader.py
ioexplorer_dataloader/loaders/FusionLoader.py
ioexplorer_dataloader/loaders/MutationLoader.py
ioexplorer_dataloader/loaders/SVLoader.py
ioexplorer_dataloader/loaders/TCRSequenceLoader.py
ioexplorer_dataloader/loaders/TimelineLoader.py
ioexplorer_dataloader/loaders/__init__.py
