Metadata-Version: 2.1
Name: ioexplorer-dataloader
Version: 0.0.15
Summary: A CLI for ingesting data into the IOExplorer database.
Home-page: UNKNOWN
Author: Ryan Marren
Author-email: rymarr@tuta.io
License: UNKNOWN
Platform: UNKNOWN
Classifier: Development Status :: 3 - Alpha
